is_url/__init__.py
is_url/cli.py
is_url/is_url.py
is_url-0.1.2.dist-info/entry_points.txt
is_url-0.1.2.dist-info/WHEEL
is_url-0.1.2.dist-info/METADATA
is_url-0.1.2.dist-info/RECORD
